<annotation>
	<folder>leo</folder>
	<filename>img23.jpg</filename>
	<path>C:\Users\leoar\Documents\n7\3A\IA\detectionNetwork\animals\leo\img23.jpg</path>
	<source>
		<database>Unknown</database>
	</source>
	<size>
		<width>64</width>
		<height>64</height>
		<depth>3</depth>
	</size>
	<segmented>0</segmented>
	<object>
		<name>chat</name>
		<pose>Unspecified</pose>
		<truncated>0</truncated>
		<difficult>0</difficult>
		<bndbox>
			<xmin>2</xmin>
			<ymin>6</ymin>
			<xmax>55</xmax>
			<ymax>56</ymax>
		</bndbox>
	</object>
</annotation>
